chains/__init__.py
chains/links/__init__.py
chains/links/link.py
chains/links/packet_meta.py
chains/links/packet_tags.py
chains/links/reverse_dns.py
chains/links/transport_tags.py
chains/sinks/__init__.py
chains/sinks/packet_logger.py
chains/sinks/packet_printer.py
chains/sinks/packet_summary.py
chains/sinks/sink.py
chains/sources/__init__.py
chains/sources/packet_streamer.py
chains/sources/source.py
chains/utils/__init__.py
chains/utils/data_utils.py
chains/utils/file_utils.py
chains/utils/log_utils.py
chains/utils/net_utils.py
py_chains-0.1.8.data/scripts/net_watch
py_chains-0.1.8.dist-info/DESCRIPTION.rst
py_chains-0.1.8.dist-info/METADATA
py_chains-0.1.8.dist-info/metadata.json
py_chains-0.1.8.dist-info/RECORD
py_chains-0.1.8.dist-info/top_level.txt
py_chains-0.1.8.dist-info/WHEEL
