Metadata-Version: 2.0
Name: py-chains
Version: 0.1.8
Summary: Exploratory Python Chained Generator Project
Home-page: https://github.com/SuperCowPowers/chains
Author: Brian Wylie
Author-email: brifordwylie@gmail.com
License: MIT
Platform: UNKNOWN
Classifier: Development Status :: 2 - Pre-Alpha
Classifier: Intended Audience :: Developers
Classifier: License :: OSI Approved :: MIT License
Classifier: Natural Language :: English
Classifier: Programming Language :: Python :: 2.6
Classifier: Programming Language :: Python :: 2.7
Classifier: Programming Language :: Python :: Implementation :: CPython
Classifier: Programming Language :: Python :: Implementation :: PyPy
Requires-Dist: pypcap
Requires-Dist: dpkt
